PyMillion/__init__.py
PyMillion/audios.py
PyMillion/caixa.py
PyMillion/main.py
PyMillion/menu.py
PyMillion/perguntas.py
PyMillion/pythonImg.py
PyMillion/sorteiaperg.py
PyMillion/textos.py
PyMillion/src/fonts/8-BIT WONDER.ttf
PyMillion/src/fonts/PixelOperator.ttf
PyMillion/src/img/PythonImg.png
PyMillion/src/sounds/acertou.wav
PyMillion/src/sounds/acertou2.wav
PyMillion/src/sounds/certeza.wav
PyMillion/src/sounds/errou.wav
PyMillion/src/sounds/musica.wav
PyMillion/src/sounds/pfinal.wav
thePyMillion-1.2.0.dist-info/LICENSE
thePyMillion-1.2.0.dist-info/METADATA
thePyMillion-1.2.0.dist-info/WHEEL
thePyMillion-1.2.0.dist-info/entry_points.txt
thePyMillion-1.2.0.dist-info/top_level.txt
thePyMillion-1.2.0.dist-info/RECORD
